statssol.py
statssol-0.7.0.dist-info/METADATA
statssol-0.7.0.dist-info/WHEEL
statssol-0.7.0.dist-info/top_level.txt
statssol-0.7.0.dist-info/RECORD
