Metadata-Version: 2.1
Name: statssol
Version: 0.7.0
Summary: stats
Home-page: https://some_website.nice
Author: **insert Author**
Author-email: some_email@mail.ru
License: UNKNOWN
Platform: UNKNOWN
Classifier: Programming Language :: Python :: 3
Classifier: License :: OSI Approved :: MIT License
Classifier: Operating System :: OS Independent
Requires-Dist: PyTelegramBotApi
Requires-Dist: cloudinary
Requires-Dist: requests
Requires-Dist: numpy
